mysql_mcp_server_pro/__init__.py
mysql_mcp_server_pro/cli.py
mysql_mcp_server_pro/server.py
mysql_mcp_server_pro/config/__init__.py
mysql_mcp_server_pro/config/dbconfig.py
mysql_mcp_server_pro/config/event_store.py
mysql_mcp_server_pro/exception/__init__.py
mysql_mcp_server_pro/exception/exceptions.py
mysql_mcp_server_pro/handles/__init__.py
mysql_mcp_server_pro/handles/base.py
mysql_mcp_server_pro/handles/execute_sql.py
mysql_mcp_server_pro/handles/get_chinese_initials.py
mysql_mcp_server_pro/handles/get_db_health_index_usage.py
mysql_mcp_server_pro/handles/get_db_health_running.py
mysql_mcp_server_pro/handles/get_table_desc.py
mysql_mcp_server_pro/handles/get_table_index.py
mysql_mcp_server_pro/handles/get_table_lock.py
mysql_mcp_server_pro/handles/get_table_name.py
mysql_mcp_server_pro/handles/optimize_sql.py
mysql_mcp_server_pro/handles/use_prompt_queryTableData.py
mysql_mcp_server_pro/oauth/__init__.py
mysql_mcp_server_pro/oauth/config.py
mysql_mcp_server_pro/oauth/middleware.py
mysql_mcp_server_pro/oauth/routes.py
mysql_mcp_server_pro/oauth/token_handler.py
mysql_mcp_server_pro/prompts/AnalysisMySqlIssues.py
mysql_mcp_server_pro/prompts/BasePrompt.py
mysql_mcp_server_pro/prompts/QueryTableData.py
mysql_mcp_server_pro/prompts/__init__.py
mysql_mcp_server_pro/templates/login.html
mysql_mcp_server_pro/utils/__init__.py
mysql_mcp_server_pro/utils/database_pool.py
mysql_mcp_server_pro/utils/execute_sql_util.py
mysql_mcp_server_pro-0.2.1.dist-info/METADATA
mysql_mcp_server_pro-0.2.1.dist-info/WHEEL
mysql_mcp_server_pro-0.2.1.dist-info/entry_points.txt
mysql_mcp_server_pro-0.2.1.dist-info/licenses/LICENSE
mysql_mcp_server_pro-0.2.1.dist-info/RECORD
