Metadata-Version: 2.4
Name: mysql_mcp_server_pro
Version: 0.2.1
Summary: Support for SSE, STDIO in MySQL MCP server, includes CRUD, database anomaly analysis capabilities .支持SSE，STDIO；不仅止于mysql的增删改查功能； 还包含了数据库异常分析能力；且便于开发者们进行个性化的工具扩展
Project-URL: Homepage, https://github.com/wenb1n-dev/mysql_mcp_server_pro
Project-URL: Documentation, https://github.com/wenb1n-dev/mysql_mcp_server_pro/blob/main/README.md
Project-URL: Repository, https://github.com/wenb1n-dev/mysql_mcp_server_pro.git
Author: wenb1n
License: MIT
License-File: LICENSE
Requires-Python: >=3.11
Requires-Dist: mcp>=1.8.0
Requires-Dist: mysql-connector-python>=9.2.0
Requires-Dist: pyjwt>=2.8.0
Requires-Dist: pymysql>=1.1.1
Requires-Dist: pypinyin>=0.54.0
Requires-Dist: python-dotenv>=1.1.0
Requires-Dist: sqlalchemy>=2.0.0
Requires-Dist: starlette>=0.46.1
Requires-Dist: uvicorn>=0.34.0
